Metadata-Version: 2.1
Name: hikapi
Version: 0.0.2
Summary: 海康的python库
Author: Chen chuan
Author-email: kcchen@139.com
Classifier: Programming Language :: Python :: 3
Classifier: License :: OSI Approved :: MIT License
Classifier: Operating System :: OS Independent
Requires-Python: >=3.5
License-File: LICENSE
